README.md
setup.py
utils_formatter_br/__init__.py
utils_formatter_br/formatters.py
utils_formatter_br.egg-info/PKG-INFO
utils_formatter_br.egg-info/SOURCES.txt
utils_formatter_br.egg-info/dependency_links.txt
utils_formatter_br.egg-info/top_level.txt