Metadata-Version: 2.1
Name: utils-formatter-br
Version: 0.0.2
Summary: UNKNOWN
Home-page: https://github.com/JuanFariasGit/utils_formatter_br_package.git
Author: Juan de Oliveira Farias
Author-email: juanfarias580@gmail.com
License: UNKNOWN
Platform: UNKNOWN
Requires-Python: >=3.8
